{
    "Role": {
        "Path": "/",
        "RoleName": "itx-lambda-archive-role",
        "RoleId": "AROAUIVCTHX7Y74NH7N3J",
        "Arn": "arn:aws:iam::293472517631:role/itx-lambda-archive-role",
        "CreateDate": "2026-03-11T14:48:24+00:00",
        "AssumeRolePolicyDocument": {
            "Version": "2012-10-17",
            "Statement": [
                {
                    "Effect": "Allow",
                    "Principal": {
                        "Service": "lambda.amazonaws.com"
                    },
                    "Action": "sts:AssumeRole"
                }
            ]
        },
        "Description": "Role for itx-archive Lambda",
        "MaxSessionDuration": 3600,
        "RoleLastUsed": {}
    }
}
